README.txt
setup.py
collective/__init__.py
collective.z3cform.filewidget.egg-info/PKG-INFO
collective.z3cform.filewidget.egg-info/SOURCES.txt
collective.z3cform.filewidget.egg-info/dependency_links.txt
collective.z3cform.filewidget.egg-info/entry_points.txt
collective.z3cform.filewidget.egg-info/namespace_packages.txt
collective.z3cform.filewidget.egg-info/not-zip-safe
collective.z3cform.filewidget.egg-info/requires.txt
collective.z3cform.filewidget.egg-info/top_level.txt
collective/z3cform/__init__.py
collective/z3cform/filewidget/__init__.py
collective/z3cform/filewidget/configure.zcml
collective/z3cform/filewidget/converter.py
collective/z3cform/filewidget/file.py
collective/z3cform/filewidget/file_display.pt
collective/z3cform/filewidget/file_input.pt
collective/z3cform/filewidget/interfaces.py
collective/z3cform/filewidget/tests.py
collective/z3cform/filewidget/version.txt
docs/HISTORY.txt
docs/INSTALL.txt
docs/LICENSE.GPL
docs/LICENSE.txt