Metadata-Version: 1.0
Name: collective.z3cform.filewidget
Version: 0.1
Summary: Simple editable filewidget for z3c forms
Home-page: http://pypi.python.org/pypi/collective.z3cform.filewidget
Author: Matous Hora
Author-email: matous.hora@dms4u.cz
License: GPL
Keywords: z3cform file widget plone
Platform: UNKNOWN
Classifier: Framework :: Plone
Classifier: Programming Language :: Python
